{
  "gerado_em": "2026-05-27T15:55:26Z",
  "posts": [
    {
      "blog": "SAFIE Cripto",
      "blog_slug": "cripto",
      "blog_url": "https://cripto.safie.blog.br",
      "cor": "#2563eb",
      "slug": "2026-05-23-estruturacao-societaria-de-empresas-cripto",
      "titulo": "Estruturação societária de empresas cripto",
      "resumo": "Com o avanço da fiscalização da Receita Federal e as novas exigências do Banco Central para prestadores de serviços de ativos virtuais (VASPs), organizar a estrutura societária de uma empresa cripto d",
      "tema": "Estruturação societária de empresas cripto",
      "data_iso": "2026-05-23",
      "data": "23 mai 2026",
      "url": "https://cripto.safie.blog.br/artigos/2026-05-23-estruturacao-societaria-de-empresas-cripto.html"
    },
    {
      "blog": "SAFIE Cripto",
      "blog_slug": "cripto",
      "blog_url": "https://cripto.safie.blog.br",
      "cor": "#2563eb",
      "slug": "2026-05-23-tributacao-de-criptoativos-no-brasil-em-2026",
      "titulo": "Tributação de Criptoativos no Brasil em 2026",
      "resumo": "O Bitcoin Pizza Day, celebrado em 22 de maio, relembra a transação de 10.000 BTC feita em 2010 para comprar duas pizzas avaliadas em US$ 41, montante que hoje representa bilhões de dólares. O episódio",
      "tema": "Tributação de criptoativos",
      "data_iso": "2026-05-23",
      "data": "23 mai 2026",
      "url": "https://cripto.safie.blog.br/artigos/2026-05-23-tributacao-de-criptoativos-no-brasil-em-2026.html"
    },
    {
      "blog": "SAFIE E-commerce",
      "blog_slug": "ecommerce",
      "blog_url": "https://ecommerce.safie.blog.br",
      "cor": "#db2777",
      "slug": "2026-05-23-publi-de-atletas-tributacao-e-compliance-digital",
      "titulo": "Publi de atletas: tributação e",
      "resumo": "A convocação de atletas para a seleção brasileira dispara contratos de publicidade em plataformas digitais, movimentando receitas que exigem enquadramento tributário correto e conformidade com as regr",
      "tema": "Marketplaces e plataformas digitais",
      "data_iso": "2026-05-23",
      "data": "23 mai 2026",
      "url": "https://ecommerce.safie.blog.br/artigos/2026-05-23-publi-de-atletas-tributacao-e-compliance-digital.html"
    },
    {
      "blog": "SAFIE E-commerce",
      "blog_slug": "ecommerce",
      "blog_url": "https://ecommerce.safie.blog.br",
      "cor": "#db2777",
      "slug": "2026-05-23-shein-compra-everlane-impacto-no-cross-border",
      "titulo": "Shein compra Everlane: impacto no",
      "resumo": "A Shein adquiriu a varejista americana Everlane, conhecida por seu posicionamento sustentável, em movimento que amplia a presença da empresa chinesa no mercado ocidental. Para o Brasil, a operação ref",
      "tema": "Importação e cross-border",
      "data_iso": "2026-05-23",
      "data": "23 mai 2026",
      "url": "https://ecommerce.safie.blog.br/artigos/2026-05-23-shein-compra-everlane-impacto-no-cross-border.html"
    },
    {
      "blog": "SAFIE Fintechs",
      "blog_slug": "fintechs",
      "blog_url": "https://fintechs.safie.blog.br",
      "cor": "#059669",
      "slug": "2026-05-23-insurtech-no-brasil-regulacao-e-oportunidades",
      "titulo": "Insurtech no Brasil: regulação e",
      "resumo": "O mercado de seguros digitais no Brasil movimenta mais de R$ 50 bilhões ao ano e opera sob regulação da SUSEP, com normas específicas para distribuição digital e microsseguros. Fintechs que atuam como",
      "tema": "Seguros digitais (insurtech)",
      "data_iso": "2026-05-23",
      "data": "23 mai 2026",
      "url": "https://fintechs.safie.blog.br/artigos/2026-05-23-insurtech-no-brasil-regulacao-e-oportunidades.html"
    },
    {
      "blog": "SAFIE Fintechs",
      "blog_slug": "fintechs",
      "blog_url": "https://fintechs.safie.blog.br",
      "cor": "#059669",
      "slug": "2026-05-23-open-finance-dados-financeiros-e-direitos-no-brasil",
      "titulo": "Open Finance: dados financeiros e direitos",
      "resumo": "O Open Finance brasileiro, regulado pelo Banco Central, estrutura o compartilhamento de dados financeiros com base no consentimento do titular e em regras técnicas específicas. Para fintechs, o sistem",
      "tema": "Open Finance e dados financeiros",
      "data_iso": "2026-05-23",
      "data": "23 mai 2026",
      "url": "https://fintechs.safie.blog.br/artigos/2026-05-23-open-finance-dados-financeiros-e-direitos-no-brasil.html"
    },
    {
      "blog": "SAFIE IA for Business",
      "blog_slug": "ia",
      "blog_url": "https://ia.safie.blog.br",
      "cor": "#7c3aed",
      "slug": "2026-05-23-lgpd-e-protecao-de-dados-em-ia-o-guia-pratico",
      "titulo": "LGPD e proteção de dados em IA: o",
      "resumo": "A LGPD impõe obrigações concretas a qualquer empresa que use dados pessoais para treinar, operar ou aprimorar sistemas de IA no Brasil. O descumprimento pode gerar multas de até 2% do faturamento, alé",
      "tema": "LGPD e proteção de dados em IA",
      "data_iso": "2026-05-23",
      "data": "23 mai 2026",
      "url": "https://ia.safie.blog.br/artigos/2026-05-23-lgpd-e-protecao-de-dados-em-ia-o-guia-pratico.html"
    },
    {
      "blog": "SAFIE IA for Business",
      "blog_slug": "ia",
      "blog_url": "https://ia.safie.blog.br",
      "cor": "#7c3aed",
      "slug": "2026-05-23-tributacao-de-empresas-de-ia-no-brasil-em-2026",
      "titulo": "Tributação de empresas de IA no",
      "resumo": "Startups de inteligência artificial operam em uma janela competitiva que pode se fechar com mudanças regulatórias e tributárias. No Brasil, a combinação de regimes fiscais favoráveis, incentivos à ino",
      "tema": "Tributação de empresas de tecnologia e IA",
      "data_iso": "2026-05-23",
      "data": "23 mai 2026",
      "url": "https://ia.safie.blog.br/artigos/2026-05-23-tributacao-de-empresas-de-ia-no-brasil-em-2026.html"
    },
    {
      "blog": "SAFIE Reforma Tributária",
      "blog_slug": "reforma-tributaria",
      "blog_url": "https://reformatributaria.safie.blog.br",
      "cor": "#b8860b",
      "slug": "2026-05-23-imposto-seletivo-o-que-muda-na-pratica",
      "titulo": "Imposto Seletivo: o que muda na",
      "resumo": "O Imposto Seletivo incide sobre produtos e serviços considerados prejudiciais à saúde ou ao meio ambiente, mas a Lei Complementar 214/2025 deixou imprecisões relevantes sobre seu fato gerador. Empresa",
      "tema": "Imposto Seletivo",
      "data_iso": "2026-05-23",
      "data": "23 mai 2026",
      "url": "https://reformatributaria.safie.blog.br/artigos/2026-05-23-imposto-seletivo-o-que-muda-na-pratica.html"
    },
    {
      "blog": "SAFIE Cripto",
      "blog_slug": "cripto",
      "blog_url": "https://cripto.safie.blog.br",
      "cor": "#2563eb",
      "slug": "2026-05-22-bitcoin-pizza-day-e-a-regulacao-cripto-no-brasil",
      "titulo": "Bitcoin Pizza Day e a regulação cripto no",
      "resumo": "Em 22 de maio de 2010, Laszlo Hanyecz pagou 10.000 BTC por duas pizzas, marcando a primeira transação comercial com Bitcoin. Dezesseis anos depois, o Brasil conta com um marco regulatório próprio para",
      "tema": "Regulação de criptoativos no Brasil",
      "data_iso": "2026-05-22",
      "data": "22 mai 2026",
      "url": "https://cripto.safie.blog.br/artigos/2026-05-22-bitcoin-pizza-day-e-a-regulacao-cripto-no-brasil.html"
    },
    {
      "blog": "SAFIE E-commerce",
      "blog_slug": "ecommerce",
      "blog_url": "https://ecommerce.safie.blog.br",
      "cor": "#db2777",
      "slug": "2026-05-22-pl-do-cdc-fiscalizacao-mais-fraca-no-e-commerce",
      "titulo": "PL do CDC: fiscalização mais fraca no",
      "resumo": "O PL 2.766/2021, pronto para votação no Senado, altera regras do Código de Defesa do Consumidor e pode tornar menos custoso para empresas descumprir obrigações legais. O secretário da Senacon alertou ",
      "tema": "Direito do consumidor no digital",
      "data_iso": "2026-05-22",
      "data": "22 mai 2026",
      "url": "https://ecommerce.safie.blog.br/artigos/2026-05-22-pl-do-cdc-fiscalizacao-mais-fraca-no-e-commerce.html"
    },
    {
      "blog": "SAFIE Fintechs",
      "blog_slug": "fintechs",
      "blog_url": "https://fintechs.safie.blog.br",
      "cor": "#059669",
      "slug": "2026-05-22-compliance-e-pld-em-fintechs-o-que-exige-a-lei",
      "titulo": "Compliance e PLD em Fintechs: o que exige",
      "resumo": "Fintechs brasileiras estão sujeitas a um conjunto robusto de obrigações de Prevenção à Lavagem de Dinheiro (PLD) e compliance regulatório, definidos principalmente pela Lei 9.613/1998, pelas resoluçõe",
      "tema": "Compliance e PLD em fintechs",
      "data_iso": "2026-05-22",
      "data": "22 mai 2026",
      "url": "https://fintechs.safie.blog.br/artigos/2026-05-22-compliance-e-pld-em-fintechs-o-que-exige-a-lei.html"
    },
    {
      "blog": "SAFIE IA for Business",
      "blog_slug": "ia",
      "blog_url": "https://ia.safie.blog.br",
      "cor": "#7c3aed",
      "slug": "2026-05-22-robbin-capta-us-108-mi-ia-e-credito-b2b-via-pix",
      "titulo": "Robbin capta US$ 108 mi: IA e",
      "resumo": "A Robbin captou US$ 108 milhões para expandir sua infraestrutura de crédito B2B baseada em Pix, sinalizando maturidade do mercado de fintechs com IA no Brasil. Do ponto de vista jurídico, a operação e",
      "tema": "Investimento em IA e deep tech",
      "data_iso": "2026-05-22",
      "data": "22 mai 2026",
      "url": "https://ia.safie.blog.br/artigos/2026-05-22-robbin-capta-us-108-mi-ia-e-credito-b2b-via-pix.html"
    },
    {
      "blog": "SAFIE Reforma Tributária",
      "blog_slug": "reforma-tributaria",
      "blog_url": "https://reformatributaria.safie.blog.br",
      "cor": "#b8860b",
      "slug": "2026-05-22-ibs-e-cbs-entenda-os-novos-tributos-da-reforma",
      "titulo": "IBS e CBS: entenda os novos",
      "resumo": "A reforma tributária criou dois novos tributos sobre o consumo: o IBS (Imposto sobre Bens e Serviços) e a CBS (Contribuição sobre Bens e Serviços). Juntos, eles substituem ICMS, ISS, PIS e COFINS, alé",
      "tema": "IBS e CBS — novos tributos",
      "data_iso": "2026-05-22",
      "data": "22 mai 2026",
      "url": "https://reformatributaria.safie.blog.br/artigos/2026-05-22-ibs-e-cbs-entenda-os-novos-tributos-da-reforma.html"
    },
    {
      "blog": "SAFIE Reforma Tributária",
      "blog_slug": "reforma-tributaria",
      "blog_url": "https://reformatributaria.safie.blog.br",
      "cor": "#b8860b",
      "slug": "2026-05-21-ibs-e-cbs-entenda-os-novos-tributos-da-reforma",
      "titulo": "IBS e CBS: entenda os novos",
      "resumo": "A reforma tributária criou dois novos tributos sobre consumo: o IBS (Imposto sobre Bens e Serviços) e a CBS (Contribuição sobre Bens e Serviços). Juntos, eles substituem cinco tributos atuais: ICMS, I",
      "tema": "IBS e CBS — novos tributos",
      "data_iso": "2026-05-21",
      "data": "21 mai 2026",
      "url": "https://reformatributaria.safie.blog.br/artigos/2026-05-21-ibs-e-cbs-entenda-os-novos-tributos-da-reforma.html"
    }
  ]
}